aws_lambda_builders/__init__.py
aws_lambda_builders/__main__.py
aws_lambda_builders/actions.py
aws_lambda_builders/architecture.py
aws_lambda_builders/binary_path.py
aws_lambda_builders/builder.py
aws_lambda_builders/exceptions.py
aws_lambda_builders/path_resolver.py
aws_lambda_builders/registry.py
aws_lambda_builders/supported_runtimes.py
aws_lambda_builders/utils.py
aws_lambda_builders/validator.py
aws_lambda_builders/workflow.py
aws_lambda_builders/workflows/__init__.py
aws_lambda_builders/workflows/custom_make/DESIGN.md
aws_lambda_builders/workflows/custom_make/__init__.py
aws_lambda_builders/workflows/custom_make/actions.py
aws_lambda_builders/workflows/custom_make/exceptions.py
aws_lambda_builders/workflows/custom_make/make.py
aws_lambda_builders/workflows/custom_make/utils.py
aws_lambda_builders/workflows/custom_make/validator.py
aws_lambda_builders/workflows/custom_make/workflow.py
aws_lambda_builders/workflows/dotnet_clipackage/DESIGN.md
aws_lambda_builders/workflows/dotnet_clipackage/__init__.py
aws_lambda_builders/workflows/dotnet_clipackage/actions.py
aws_lambda_builders/workflows/dotnet_clipackage/dotnetcli.py
aws_lambda_builders/workflows/dotnet_clipackage/dotnetcli_resolver.py
aws_lambda_builders/workflows/dotnet_clipackage/utils.py
aws_lambda_builders/workflows/dotnet_clipackage/workflow.py
aws_lambda_builders/workflows/go_modules/DESIGN.md
aws_lambda_builders/workflows/go_modules/__init__.py
aws_lambda_builders/workflows/go_modules/actions.py
aws_lambda_builders/workflows/go_modules/builder.py
aws_lambda_builders/workflows/go_modules/utils.py
aws_lambda_builders/workflows/go_modules/validator.py
aws_lambda_builders/workflows/go_modules/workflow.py
aws_lambda_builders/workflows/java/__init__.py
aws_lambda_builders/workflows/java/actions.py
aws_lambda_builders/workflows/java/utils.py
aws_lambda_builders/workflows/java_gradle/DESIGN.md
aws_lambda_builders/workflows/java_gradle/__init__.py
aws_lambda_builders/workflows/java_gradle/actions.py
aws_lambda_builders-1.62.0.dist-info/licenses/LICENSE
aws_lambda_builders-1.62.0.dist-info/licenses/NOTICE
aws_lambda_builders-1.62.0.dist-info/METADATA
aws_lambda_builders-1.62.0.dist-info/WHEEL
aws_lambda_builders-1.62.0.dist-info/entry_points.txt
aws_lambda_builders-1.62.0.dist-info/top_level.txt
aws_lambda_builders-1.62.0.dist-info/RECORD
