Metadata-Version: 2.4
Name: aws_lambda_builders
Version: 1.62.0
Summary: Python library to compile, build & package AWS Lambda functions for several runtimes & frameworks.
Home-page: https://github.com/awslabs/aws-lambda-builders
Author: Amazon Web Services
Author-email: aws-sam-developers@amazon.com
License: Apache License 2.0
Keywords: AWS Lambda Functions Building
Classifier: Development Status :: 4 - Beta
Classifier: Environment :: Console
Classifier: Environment :: Other Environment
Classifier: Intended Audience :: Developers
Classifier: Intended Audience :: Information Technology
Classifier: License :: OSI Approved :: Apache Software License
Classifier: Operating System :: OS Independent
Classifier: Programming Language :: Python
Classifier: Programming Language :: Python :: 3.8
Classifier: Programming Language :: Python :: 3.9
Classifier: Programming Language :: Python :: 3.10
Classifier: Programming Language :: Python :: 3.11
Classifier: Programming Language :: Python :: 3.12
Classifier: Programming Language :: Python :: 3.13
Classifier: Programming Language :: Python :: 3.14
Classifier: Topic :: Internet
Classifier: Topic :: Software Development :: Build Tools
Classifier: Topic :: Utilities
Requires-Python: >=3.8
License-File: LICENSE
License-File: NOTICE
Requires-Dist: setuptools
Requires-Dist: wheel
Provides-Extra: dev
Requires-Dist: coverage==7.10.7; python_version >= "3.9" and extra == "dev"
Requires-Dist: coverage==7.6.1; python_version < "3.9" and extra == "dev"
Requires-Dist: flake8==3.8.4; extra == "dev"
Requires-Dist: pytest-cov==6.3.0; python_version >= "3.9" and extra == "dev"
Requires-Dist: pytest-cov==5.0.0; python_version < "3.9" and extra == "dev"
Requires-Dist: pytest>=6.1.1; extra == "dev"
Requires-Dist: parameterized==0.9.0; extra == "dev"
Requires-Dist: pyelftools~=0.32; extra == "dev"
Requires-Dist: black==25.11.0; python_version >= "3.9" and extra == "dev"
Requires-Dist: black==24.8.0; python_version < "3.9" and extra == "dev"
Requires-Dist: ruff==0.14.13; extra == "dev"
Dynamic: author
Dynamic: author-email
Dynamic: classifier
Dynamic: description
Dynamic: home-page
Dynamic: keywords
Dynamic: license
Dynamic: license-file
Dynamic: provides-extra
Dynamic: requires-dist
Dynamic: requires-python
Dynamic: summary
